{"api_index.md":"-goSOGr7","guide_acknowledgements.md":"BldDBD68","guide_benchmarks_benchmarks.md":"1zK_909D","guide_binary_bit-byte-vector.md":"DPgXpzOg","guide_binary_crc.md":"F_hBRtdV","guide_binary_encoding-and-decoding.md":"Cy534cAx","guide_binary_streaming.md":"cXF7vGo8","guide_check_property-based-testing.md":"BB0_T26k","guide_core_collections_map.md":"D99gtATD","guide_core_collections_overview.md":"BxuDWsAk","guide_core_collections_sequence.md":"HQtvfJT-","guide_core_collections_set.md":"CSCzkFQD","guide_core_either.md":"CViAjhfE","guide_core_functions.md":"DxXe-uS3","guide_core_option.md":"B0-3kFeE","guide_core_state.md":"2AYNJ2Kg","guide_core_syntax.md":"DXG2iAUw","guide_core_unit.md":"jrGU3kUj","guide_core_validated.md":"DZ-Fb4Mb","guide_effect_count-down-latch.md":"Czx5W6WR","guide_effect_cyclic-barrier.md":"BRbBYlyT","guide_effect_deferred.md":"DUjwMyEP","guide_effect_dispatcher.md":"U4YsTN1K","guide_effect_io-retry.md":"BBdiO2jO","guide_effect_io.md":"DRX9s0d3","guide_effect_overview.md":"DMo7KwvD","guide_effect_queue.md":"rT3s8qDc","guide_effect_ref.md":"BAO7dnoj","guide_effect_resource.md":"lDexJkli","guide_effect_semaphore.md":"BQ--4uFu","guide_effect_supervisor.md":"DoFKxR16","guide_effect_testing.md":"199zDlz3","guide_effect_tracing.md":"CaunfYyt","guide_index.md":"BB6ySYPa","guide_json_creating-json.md":"BtII-2sg","guide_json_encoding-and-decoding.md":"DvZOt2qM","guide_json_parsing-json.md":"BbkRJ0Gd","guide_json_streaming.md":"DkjUAY8Z","guide_limiter_overview.md":"wfV-Q7lh","guide_motivation.md":"CVDmmMgK","guide_optics_iso.md":"DGiZEQzl","guide_optics_lens.md":"DprhkCps","guide_optics_optional.md":"CIKXPNaj","guide_optics_overview.md":"CYc3xsT8","guide_optics_prism.md":"BFCGkV1H","guide_overview.md":"W7eGUDTX","guide_rill_arill.md":"Cd4_2kTq","guide_rill_channel.md":"By6f1lIX","guide_rill_chunk.md":"DUWlfXsB","guide_rill_pipe.md":"Ddm4tvQL","guide_rill_pull.md":"BLnQyXpG","guide_rill_rill_io.md":"HlRSLCvR","guide_rill_signal.md":"Bpv906t4","guide_rill_topic.md":"Bhbfmv--","guide_sql_overview.md":"CWauI9AP","guide_sql_postgres.md":"CIDM43MG","guide_sql_sqlite.md":"BtpvRNFD","guide_units_motivation.md":"B4aiSMTc","index.md":"BilZuKtv"}
